{
  "schema": "fem_swing_timesfm_overlay/v1",
  "generated_at": "2026-07-23T14:57:21-04:00",
  "day": "2026-07-23",
  "source_schema": "fem_channel_shelf_reclaim_swing.v2",
  "source_generated_at": "2026-07-23T11:51:20",
  "source_candidate_count": 3,
  "permission": "SHADOW_ONLY",
  "model": {
    "source": "timesfm_2p5",
    "timesfm_error": null,
    "mode": "auto",
    "timeframes": {
      "15m": {
        "multiplier": 15,
        "timespan": "minute",
        "lookback_days": 70,
        "horizon_bars": 16,
        "context_bars": 384,
        "weight": 0.55,
        "meaning": "next intraday/1-2 day reclaim timing"
      },
      "60m": {
        "multiplier": 1,
        "timespan": "hour",
        "lookback_days": 220,
        "horizon_bars": 12,
        "context_bars": 384,
        "weight": 0.45,
        "meaning": "swing follow-through / rollover risk"
      }
    },
    "notes": [
      "Overlay only; does not place trades.",
      "Forecast scores only FEM Swing/NBIS structural candidates.",
      "FORECAST_RECLAIM_SUPPORTS means timing favors continuation toward the next shelf/recent high.",
      "FORECAST_WAIT means structure is interesting but forecast timing is not enough.",
      "FORECAST_ROLLOVER_RISK means the model sees higher breakdown/stop risk."
    ]
  },
  "counts": {
    "scored": 3,
    "supports": 2,
    "wait": 1,
    "rollover_risk": 0,
    "no_forecast": 0
  },
  "top": [
    {
      "ticker": "COCO",
      "phase": "EARLY_RECLAIM_TRIGGER",
      "swing_score": 100.0,
      "nbis_similarity_score": 100.0,
      "pre_move_score": 100.0,
      "timing": {
        "bucket": "EARLY_RECLAIM_TRIGGER",
        "already_extended": false,
        "extension_flags": [],
        "reclaim_dist_pct": 2.44,
        "extension_from_reclaim_pct": 2.5,
        "near_trigger": true,
        "under_or_at_trigger": false,
        "just_reclaimed": true,
        "tagged_not_reclaimed": false,
        "low_or_mid_channel": true
      },
      "price": 68.985,
      "room_to_recent_high_pct": 28.45,
      "support_stack_depth": 11,
      "parent_gap": {
        "lo": 51.63,
        "hi": 60.63,
        "mid": 56.13,
        "tf": "daily",
        "type": "gap",
        "tick_width": 900,
        "creation_vol": 5754004.0,
        "genesis_rank_pct": 100.0
      },
      "reclaim": {
        "level": 67.3,
        "source": "nearest_support_gap_hi",
        "dist_pct": 2.44,
        "recent_tagged": true,
        "reclaimed": true,
        "tag_tf": "15m",
        "tag_low": 67.3202,
        "last_close": 70.385
      },
      "channel": {
        "tf": "daily",
        "method": "log_regression",
        "direction": "ASC",
        "score": 84.86,
        "position": "AT_LOWER",
        "position_ratio": 0.301,
        "lower_rail": 56.57,
        "upper_rail": 97.81,
        "rail_width": 41.23
      },
      "gap_options_agreement": {
        "label": "OPTIONS_MISSING",
        "raw": {
          "agreement": null,
          "call_wall": null,
          "put_wall": null,
          "source": null
        }
      },
      "timesfm_swing": {
        "decision": "FORECAST_RECLAIM_SUPPORTS",
        "timing_score": 77.3,
        "support_votes": 1,
        "risk_votes": 0,
        "flags": [
          "near_target_supported",
          "positive_median_drift",
          "reclaim_supported"
        ]
      },
      "timeframes": {
        "15m": {
          "model_source": "timesfm_2p5",
          "decision": "FORECAST_WAIT",
          "timing_score": 73.5,
          "p_near_target": 0.56,
          "p_swing_target": 0.01,
          "p_stop": 0.075,
          "p_reclaim": 0.901,
          "edge": 0.485,
          "swing_edge": -0.065,
          "last": 71.1,
          "forecast_final": 70.7671,
          "q10_min": 68.1891,
          "q50_final": 70.7671,
          "q90_max": 74.3666,
          "median_ret_pct": -0.47,
          "horizon_bars": 16,
          "targets": {
            "price": 68.985,
            "stop": 51.3719,
            "reclaim": 67.3,
            "near_target": 70.38,
            "swing_target": 88.61
          },
          "flags": [
            "near_target_supported",
            "reclaim_supported"
          ],
          "bars": 384,
          "bars_asof": "2026-07-23 14:45:00",
          "tf": "15m",
          "meaning": "next intraday/1-2 day reclaim timing"
        },
        "60m": {
          "model_source": "timesfm_2p5",
          "decision": "FORECAST_RECLAIM_SUPPORTS",
          "timing_score": 81.9,
          "p_near_target": 0.682,
          "p_swing_target": 0.01,
          "p_stop": 0.075,
          "p_reclaim": 0.902,
          "edge": 0.608,
          "swing_edge": -0.065,
          "last": 71.1,
          "forecast_final": 71.812,
          "q10_min": 68.6732,
          "q50_final": 71.812,
          "q90_max": 75.6224,
          "median_ret_pct": 1.0,
          "horizon_bars": 12,
          "targets": {
            "price": 68.985,
            "stop": 51.3719,
            "reclaim": 67.3,
            "near_target": 70.38,
            "swing_target": 88.61
          },
          "flags": [
            "near_target_supported",
            "reclaim_supported",
            "positive_median_drift"
          ],
          "bars": 384,
          "bars_asof": "2026-07-23 14:00:00",
          "tf": "60m",
          "meaning": "swing follow-through / rollover risk"
        }
      },
      "permission": "SHADOW_ONLY"
    },
    {
      "ticker": "TSLA",
      "phase": "EARLY_STRUCTURAL_MATCH",
      "swing_score": 68.7,
      "nbis_similarity_score": 66.0,
      "pre_move_score": 66.0,
      "timing": {
        "bucket": "TOO_EARLY_OR_LOOSE",
        "already_extended": false,
        "extension_flags": [],
        "reclaim_dist_pct": -3.71,
        "extension_from_reclaim_pct": -3.58,
        "near_trigger": false,
        "under_or_at_trigger": false,
        "just_reclaimed": false,
        "tagged_not_reclaimed": true,
        "low_or_mid_channel": true
      },
      "price": 322.75,
      "room_to_recent_high_pct": 40.48,
      "support_stack_depth": 4,
      "parent_gap": {
        "lo": 237.97,
        "hi": 250.74,
        "mid": 244.355,
        "tf": "daily",
        "type": "gap",
        "tick_width": 1278,
        "creation_vol": 150381903.0,
        "genesis_rank_pct": 98.88
      },
      "reclaim": {
        "level": 334.72,
        "source": "lower",
        "dist_pct": -3.71,
        "recent_tagged": true,
        "reclaimed": false,
        "tag_tf": "15m",
        "tag_low": 318.55,
        "last_close": 324.6
      },
      "channel": {
        "tf": "weekly",
        "method": "log_regression",
        "direction": "ASC",
        "score": 42.92,
        "position": "OUTSIDE_DOWN",
        "position_ratio": -0.057,
        "lower_rail": 334.72,
        "upper_rail": 546.08,
        "rail_width": 211.37
      },
      "gap_options_agreement": {
        "label": "OPTIONS_NOT_CHECKED",
        "raw": null
      },
      "timesfm_swing": {
        "decision": "FORECAST_RECLAIM_SUPPORTS",
        "timing_score": 64.2,
        "support_votes": 1,
        "risk_votes": 0,
        "flags": [
          "near_target_supported",
          "reclaim_supported"
        ]
      },
      "timeframes": {
        "15m": {
          "model_source": "timesfm_2p5",
          "decision": "FORECAST_WAIT",
          "timing_score": 42.4,
          "p_near_target": 0.093,
          "p_swing_target": 0.01,
          "p_stop": 0.075,
          "p_reclaim": 0.037,
          "edge": 0.018,
          "swing_edge": -0.065,
          "last": 321.07,
          "forecast_final": 320.3909,
          "q10_min": 315.3895,
          "q50_final": 320.3909,
          "q90_max": 328.8347,
          "median_ret_pct": -0.21,
          "horizon_bars": 16,
          "targets": {
            "price": 322.75,
            "stop": 236.7801,
            "reclaim": 334.72,
            "near_target": 329.52,
            "swing_target": 453.4
          },
          "flags": [],
          "bars": 384,
          "bars_asof": "2026-07-23 14:45:00",
          "tf": "15m",
          "meaning": "next intraday/1-2 day reclaim timing"
        },
        "60m": {
          "model_source": "timesfm_2p5",
          "decision": "FORECAST_RECLAIM_SUPPORTS",
          "timing_score": 90.8,
          "p_near_target": 0.917,
          "p_swing_target": 0.01,
          "p_stop": 0.06,
          "p_reclaim": 0.915,
          "edge": 0.857,
          "swing_edge": -0.05,
          "last": 405.425,
          "forecast_final": 405.6789,
          "q10_min": 395.5718,
          "q50_final": 405.6789,
          "q90_max": 414.0143,
          "median_ret_pct": 0.06,
          "horizon_bars": 12,
          "targets": {
            "price": 322.75,
            "stop": 236.7801,
            "reclaim": 334.72,
            "near_target": 329.52,
            "swing_target": 453.4
          },
          "flags": [
            "near_target_supported",
            "reclaim_supported"
          ],
          "bars": 384,
          "bars_asof": "2026-03-04 14:00:00",
          "tf": "60m",
          "meaning": "swing follow-through / rollover risk"
        }
      },
      "permission": "SHADOW_ONLY"
    },
    {
      "ticker": "LPG",
      "phase": "EARLY_RECLAIM_TRIGGER",
      "swing_score": 100.0,
      "nbis_similarity_score": 93.0,
      "pre_move_score": 93.0,
      "timing": {
        "bucket": "EARLY_RECLAIM_TRIGGER",
        "already_extended": false,
        "extension_flags": [],
        "reclaim_dist_pct": 2.28,
        "extension_from_reclaim_pct": 2.33,
        "near_trigger": true,
        "under_or_at_trigger": false,
        "just_reclaimed": true,
        "tagged_not_reclaimed": false,
        "low_or_mid_channel": true
      },
      "price": 45.395,
      "room_to_recent_high_pct": 6.0,
      "support_stack_depth": 46,
      "parent_gap": {
        "lo": 40.05,
        "hi": 40.6,
        "mid": 40.325,
        "tf": "weekly",
        "type": "vi",
        "tick_width": 56,
        "creation_vol": 3463822.0,
        "genesis_rank_pct": 100.0
      },
      "reclaim": {
        "level": 44.36,
        "source": "nearest_support_gap_hi",
        "dist_pct": 2.28,
        "recent_tagged": true,
        "reclaimed": true,
        "tag_tf": "15m",
        "tag_low": 43.84,
        "last_close": 45.42
      },
      "channel": {
        "tf": "daily",
        "method": "log_regression",
        "direction": "ASC",
        "score": 71.83,
        "position": "MID",
        "position_ratio": 0.513,
        "lower_rail": 36.42,
        "upper_rail": 53.93,
        "rail_width": 17.51
      },
      "gap_options_agreement": {
        "label": "OPTIONS_MISSING",
        "raw": {
          "agreement": null,
          "call_wall": null,
          "put_wall": null,
          "source": null
        }
      },
      "timesfm_swing": {
        "decision": "FORECAST_WAIT",
        "timing_score": 50.2,
        "support_votes": 0,
        "risk_votes": 0,
        "flags": [
          "reclaim_supported"
        ]
      },
      "timeframes": {
        "15m": {
          "model_source": "timesfm_2p5",
          "decision": "FORECAST_WAIT",
          "timing_score": 50.0,
          "p_near_target": 0.01,
          "p_swing_target": 0.01,
          "p_stop": 0.09,
          "p_reclaim": 0.85,
          "edge": -0.08,
          "swing_edge": -0.08,
          "last": 45.27,
          "forecast_final": 45.3085,
          "q10_min": 44.2239,
          "q50_final": 45.3085,
          "q90_max": 45.9809,
          "median_ret_pct": 0.09,
          "horizon_bars": 16,
          "targets": {
            "price": 45.395,
            "stop": 39.8498,
            "reclaim": 44.36,
            "near_target": 47.62,
            "swing_target": 48.12
          },
          "flags": [
            "reclaim_supported"
          ],
          "bars": 384,
          "bars_asof": "2026-07-23 14:45:00",
          "tf": "15m",
          "meaning": "next intraday/1-2 day reclaim timing"
        },
        "60m": {
          "model_source": "timesfm_2p5",
          "decision": "FORECAST_WAIT",
          "timing_score": 50.5,
          "p_near_target": 0.065,
          "p_swing_target": 0.038,
          "p_stop": 0.092,
          "p_reclaim": 0.705,
          "edge": -0.027,
          "swing_edge": -0.053,
          "last": 45.27,
          "forecast_final": 45.2509,
          "q10_min": 43.5107,
          "q50_final": 45.2509,
          "q90_max": 46.9508,
          "median_ret_pct": -0.04,
          "horizon_bars": 12,
          "targets": {
            "price": 45.395,
            "stop": 39.8498,
            "reclaim": 44.36,
            "near_target": 47.62,
            "swing_target": 48.12
          },
          "flags": [
            "reclaim_supported"
          ],
          "bars": 384,
          "bars_asof": "2026-07-23 14:00:00",
          "tf": "60m",
          "meaning": "swing follow-through / rollover risk"
        }
      },
      "permission": "SHADOW_ONLY"
    }
  ],
  "by_ticker": {
    "COCO": {
      "ticker": "COCO",
      "phase": "EARLY_RECLAIM_TRIGGER",
      "swing_score": 100.0,
      "nbis_similarity_score": 100.0,
      "pre_move_score": 100.0,
      "timing": {
        "bucket": "EARLY_RECLAIM_TRIGGER",
        "already_extended": false,
        "extension_flags": [],
        "reclaim_dist_pct": 2.44,
        "extension_from_reclaim_pct": 2.5,
        "near_trigger": true,
        "under_or_at_trigger": false,
        "just_reclaimed": true,
        "tagged_not_reclaimed": false,
        "low_or_mid_channel": true
      },
      "price": 68.985,
      "room_to_recent_high_pct": 28.45,
      "support_stack_depth": 11,
      "parent_gap": {
        "lo": 51.63,
        "hi": 60.63,
        "mid": 56.13,
        "tf": "daily",
        "type": "gap",
        "tick_width": 900,
        "creation_vol": 5754004.0,
        "genesis_rank_pct": 100.0
      },
      "reclaim": {
        "level": 67.3,
        "source": "nearest_support_gap_hi",
        "dist_pct": 2.44,
        "recent_tagged": true,
        "reclaimed": true,
        "tag_tf": "15m",
        "tag_low": 67.3202,
        "last_close": 70.385
      },
      "channel": {
        "tf": "daily",
        "method": "log_regression",
        "direction": "ASC",
        "score": 84.86,
        "position": "AT_LOWER",
        "position_ratio": 0.301,
        "lower_rail": 56.57,
        "upper_rail": 97.81,
        "rail_width": 41.23
      },
      "gap_options_agreement": {
        "label": "OPTIONS_MISSING",
        "raw": {
          "agreement": null,
          "call_wall": null,
          "put_wall": null,
          "source": null
        }
      },
      "timesfm_swing": {
        "decision": "FORECAST_RECLAIM_SUPPORTS",
        "timing_score": 77.3,
        "support_votes": 1,
        "risk_votes": 0,
        "flags": [
          "near_target_supported",
          "positive_median_drift",
          "reclaim_supported"
        ]
      },
      "timeframes": {
        "15m": {
          "model_source": "timesfm_2p5",
          "decision": "FORECAST_WAIT",
          "timing_score": 73.5,
          "p_near_target": 0.56,
          "p_swing_target": 0.01,
          "p_stop": 0.075,
          "p_reclaim": 0.901,
          "edge": 0.485,
          "swing_edge": -0.065,
          "last": 71.1,
          "forecast_final": 70.7671,
          "q10_min": 68.1891,
          "q50_final": 70.7671,
          "q90_max": 74.3666,
          "median_ret_pct": -0.47,
          "horizon_bars": 16,
          "targets": {
            "price": 68.985,
            "stop": 51.3719,
            "reclaim": 67.3,
            "near_target": 70.38,
            "swing_target": 88.61
          },
          "flags": [
            "near_target_supported",
            "reclaim_supported"
          ],
          "bars": 384,
          "bars_asof": "2026-07-23 14:45:00",
          "tf": "15m",
          "meaning": "next intraday/1-2 day reclaim timing"
        },
        "60m": {
          "model_source": "timesfm_2p5",
          "decision": "FORECAST_RECLAIM_SUPPORTS",
          "timing_score": 81.9,
          "p_near_target": 0.682,
          "p_swing_target": 0.01,
          "p_stop": 0.075,
          "p_reclaim": 0.902,
          "edge": 0.608,
          "swing_edge": -0.065,
          "last": 71.1,
          "forecast_final": 71.812,
          "q10_min": 68.6732,
          "q50_final": 71.812,
          "q90_max": 75.6224,
          "median_ret_pct": 1.0,
          "horizon_bars": 12,
          "targets": {
            "price": 68.985,
            "stop": 51.3719,
            "reclaim": 67.3,
            "near_target": 70.38,
            "swing_target": 88.61
          },
          "flags": [
            "near_target_supported",
            "reclaim_supported",
            "positive_median_drift"
          ],
          "bars": 384,
          "bars_asof": "2026-07-23 14:00:00",
          "tf": "60m",
          "meaning": "swing follow-through / rollover risk"
        }
      },
      "permission": "SHADOW_ONLY"
    },
    "TSLA": {
      "ticker": "TSLA",
      "phase": "EARLY_STRUCTURAL_MATCH",
      "swing_score": 68.7,
      "nbis_similarity_score": 66.0,
      "pre_move_score": 66.0,
      "timing": {
        "bucket": "TOO_EARLY_OR_LOOSE",
        "already_extended": false,
        "extension_flags": [],
        "reclaim_dist_pct": -3.71,
        "extension_from_reclaim_pct": -3.58,
        "near_trigger": false,
        "under_or_at_trigger": false,
        "just_reclaimed": false,
        "tagged_not_reclaimed": true,
        "low_or_mid_channel": true
      },
      "price": 322.75,
      "room_to_recent_high_pct": 40.48,
      "support_stack_depth": 4,
      "parent_gap": {
        "lo": 237.97,
        "hi": 250.74,
        "mid": 244.355,
        "tf": "daily",
        "type": "gap",
        "tick_width": 1278,
        "creation_vol": 150381903.0,
        "genesis_rank_pct": 98.88
      },
      "reclaim": {
        "level": 334.72,
        "source": "lower",
        "dist_pct": -3.71,
        "recent_tagged": true,
        "reclaimed": false,
        "tag_tf": "15m",
        "tag_low": 318.55,
        "last_close": 324.6
      },
      "channel": {
        "tf": "weekly",
        "method": "log_regression",
        "direction": "ASC",
        "score": 42.92,
        "position": "OUTSIDE_DOWN",
        "position_ratio": -0.057,
        "lower_rail": 334.72,
        "upper_rail": 546.08,
        "rail_width": 211.37
      },
      "gap_options_agreement": {
        "label": "OPTIONS_NOT_CHECKED",
        "raw": null
      },
      "timesfm_swing": {
        "decision": "FORECAST_RECLAIM_SUPPORTS",
        "timing_score": 64.2,
        "support_votes": 1,
        "risk_votes": 0,
        "flags": [
          "near_target_supported",
          "reclaim_supported"
        ]
      },
      "timeframes": {
        "15m": {
          "model_source": "timesfm_2p5",
          "decision": "FORECAST_WAIT",
          "timing_score": 42.4,
          "p_near_target": 0.093,
          "p_swing_target": 0.01,
          "p_stop": 0.075,
          "p_reclaim": 0.037,
          "edge": 0.018,
          "swing_edge": -0.065,
          "last": 321.07,
          "forecast_final": 320.3909,
          "q10_min": 315.3895,
          "q50_final": 320.3909,
          "q90_max": 328.8347,
          "median_ret_pct": -0.21,
          "horizon_bars": 16,
          "targets": {
            "price": 322.75,
            "stop": 236.7801,
            "reclaim": 334.72,
            "near_target": 329.52,
            "swing_target": 453.4
          },
          "flags": [],
          "bars": 384,
          "bars_asof": "2026-07-23 14:45:00",
          "tf": "15m",
          "meaning": "next intraday/1-2 day reclaim timing"
        },
        "60m": {
          "model_source": "timesfm_2p5",
          "decision": "FORECAST_RECLAIM_SUPPORTS",
          "timing_score": 90.8,
          "p_near_target": 0.917,
          "p_swing_target": 0.01,
          "p_stop": 0.06,
          "p_reclaim": 0.915,
          "edge": 0.857,
          "swing_edge": -0.05,
          "last": 405.425,
          "forecast_final": 405.6789,
          "q10_min": 395.5718,
          "q50_final": 405.6789,
          "q90_max": 414.0143,
          "median_ret_pct": 0.06,
          "horizon_bars": 12,
          "targets": {
            "price": 322.75,
            "stop": 236.7801,
            "reclaim": 334.72,
            "near_target": 329.52,
            "swing_target": 453.4
          },
          "flags": [
            "near_target_supported",
            "reclaim_supported"
          ],
          "bars": 384,
          "bars_asof": "2026-03-04 14:00:00",
          "tf": "60m",
          "meaning": "swing follow-through / rollover risk"
        }
      },
      "permission": "SHADOW_ONLY"
    },
    "LPG": {
      "ticker": "LPG",
      "phase": "EARLY_RECLAIM_TRIGGER",
      "swing_score": 100.0,
      "nbis_similarity_score": 93.0,
      "pre_move_score": 93.0,
      "timing": {
        "bucket": "EARLY_RECLAIM_TRIGGER",
        "already_extended": false,
        "extension_flags": [],
        "reclaim_dist_pct": 2.28,
        "extension_from_reclaim_pct": 2.33,
        "near_trigger": true,
        "under_or_at_trigger": false,
        "just_reclaimed": true,
        "tagged_not_reclaimed": false,
        "low_or_mid_channel": true
      },
      "price": 45.395,
      "room_to_recent_high_pct": 6.0,
      "support_stack_depth": 46,
      "parent_gap": {
        "lo": 40.05,
        "hi": 40.6,
        "mid": 40.325,
        "tf": "weekly",
        "type": "vi",
        "tick_width": 56,
        "creation_vol": 3463822.0,
        "genesis_rank_pct": 100.0
      },
      "reclaim": {
        "level": 44.36,
        "source": "nearest_support_gap_hi",
        "dist_pct": 2.28,
        "recent_tagged": true,
        "reclaimed": true,
        "tag_tf": "15m",
        "tag_low": 43.84,
        "last_close": 45.42
      },
      "channel": {
        "tf": "daily",
        "method": "log_regression",
        "direction": "ASC",
        "score": 71.83,
        "position": "MID",
        "position_ratio": 0.513,
        "lower_rail": 36.42,
        "upper_rail": 53.93,
        "rail_width": 17.51
      },
      "gap_options_agreement": {
        "label": "OPTIONS_MISSING",
        "raw": {
          "agreement": null,
          "call_wall": null,
          "put_wall": null,
          "source": null
        }
      },
      "timesfm_swing": {
        "decision": "FORECAST_WAIT",
        "timing_score": 50.2,
        "support_votes": 0,
        "risk_votes": 0,
        "flags": [
          "reclaim_supported"
        ]
      },
      "timeframes": {
        "15m": {
          "model_source": "timesfm_2p5",
          "decision": "FORECAST_WAIT",
          "timing_score": 50.0,
          "p_near_target": 0.01,
          "p_swing_target": 0.01,
          "p_stop": 0.09,
          "p_reclaim": 0.85,
          "edge": -0.08,
          "swing_edge": -0.08,
          "last": 45.27,
          "forecast_final": 45.3085,
          "q10_min": 44.2239,
          "q50_final": 45.3085,
          "q90_max": 45.9809,
          "median_ret_pct": 0.09,
          "horizon_bars": 16,
          "targets": {
            "price": 45.395,
            "stop": 39.8498,
            "reclaim": 44.36,
            "near_target": 47.62,
            "swing_target": 48.12
          },
          "flags": [
            "reclaim_supported"
          ],
          "bars": 384,
          "bars_asof": "2026-07-23 14:45:00",
          "tf": "15m",
          "meaning": "next intraday/1-2 day reclaim timing"
        },
        "60m": {
          "model_source": "timesfm_2p5",
          "decision": "FORECAST_WAIT",
          "timing_score": 50.5,
          "p_near_target": 0.065,
          "p_swing_target": 0.038,
          "p_stop": 0.092,
          "p_reclaim": 0.705,
          "edge": -0.027,
          "swing_edge": -0.053,
          "last": 45.27,
          "forecast_final": 45.2509,
          "q10_min": 43.5107,
          "q50_final": 45.2509,
          "q90_max": 46.9508,
          "median_ret_pct": -0.04,
          "horizon_bars": 12,
          "targets": {
            "price": 45.395,
            "stop": 39.8498,
            "reclaim": 44.36,
            "near_target": 47.62,
            "swing_target": 48.12
          },
          "flags": [
            "reclaim_supported"
          ],
          "bars": 384,
          "bars_asof": "2026-07-23 14:00:00",
          "tf": "60m",
          "meaning": "swing follow-through / rollover risk"
        }
      },
      "permission": "SHADOW_ONLY"
    }
  }
}