{
  "schema": "fem_live_fire_grade/v1",
  "generated_at": "2026-07-06T04:37:46",
  "asof_date": "2026-07-06",
  "grade_window_min": 30,
  "takeoff_pct": 3.0,
  "n_total": 137,
  "by_kind": {
    "surge": {
      "n": 0,
      "n_fires_raw": 0,
      "ran_rate": null,
      "avg_max_up_pct": null,
      "win_pct": null,
      "avg_r": null,
      "verdict": "NEED MORE DATA"
    },
    "gap_eat": {
      "n": 0,
      "n_fires_raw": 0,
      "ran_rate": null,
      "avg_max_up_pct": null,
      "win_pct": null,
      "avg_r": null,
      "verdict": "NEED MORE DATA"
    },
    "dump": {
      "n": 64,
      "n_fires_raw": 64,
      "ran_rate": 0.031,
      "avg_max_up_pct": 0.68,
      "win_pct": 1.6,
      "avg_r": -0.96,
      "verdict": "BAD",
      "median_mins_to_peak": 7.0
    },
    "reclaim": {
      "n": 0,
      "n_fires_raw": 0,
      "ran_rate": null,
      "avg_max_up_pct": null,
      "win_pct": null,
      "avg_r": null,
      "verdict": "NEED MORE DATA"
    },
    "gap_reclaim": {
      "n": 0,
      "n_fires_raw": 0,
      "ran_rate": null,
      "avg_max_up_pct": null,
      "win_pct": null,
      "avg_r": null,
      "verdict": "NEED MORE DATA"
    }
  },
  "recent": [
    {
      "kind": "dump",
      "ticker": "JZXN",
      "t": "2026-07-06T07:07:00-04:00",
      "fire_min": 427,
      "entry": 1.23,
      "rel_vol": 15.1,
      "move_pct": -7.35,
      "target": null,
      "stop": null,
      "regime": "RISK_OFF",
      "graded": true,
      "contract_trace_id": "2026-07-06:live_fire:JZXN:SHORT:dump:706T0707000400:c38469dd",
      "max_up_pct": 14.63,
      "ran": true,
      "mins_to_peak": 0
    },
    {
      "kind": "dump",
      "ticker": "AA",
      "t": "2026-07-06T07:04:11-04:00",
      "fire_min": 424,
      "entry": 49.76,
      "rel_vol": null,
      "move_pct": 0.48,
      "target": 49.08,
      "stop": 50.1,
      "regime": null,
      "graded": true,
      "contract_trace_id": "2026-07-06:live_fire:AA:SHORT:dump:706T0704110400:5b9539fc",
      "max_up_pct": 0.0,
      "ran": false,
      "mins_to_peak": null
    },
    {
      "kind": "dump",
      "ticker": "AAOI",
      "t": "2026-07-06T07:04:11-04:00",
      "fire_min": 424,
      "entry": 118.68,
      "rel_vol": null,
      "move_pct": 0.07,
      "target": 114.1372,
      "stop": 120.9514,
      "regime": null,
      "graded": true,
      "contract_trace_id": "2026-07-06:live_fire:AAOI:SHORT:dump:706T0704110400:544ba33f",
      "max_up_pct": 0.19,
      "ran": false,
      "mins_to_peak": 4
    },
    {
      "kind": "dump",
      "ticker": "ABVX",
      "t": "2026-07-06T07:04:11-04:00",
      "fire_min": 424,
      "entry": 148.15,
      "rel_vol": null,
      "move_pct": 0.0,
      "target": 140.6836,
      "stop": 151.8832,
      "regime": null,
      "graded": true,
      "contract_trace_id": "2026-07-06:live_fire:ABVX:SHORT:dump:706T0704110400:523f5239",
      "max_up_pct": 0.26,
      "ran": false,
      "mins_to_peak": 0
    },
    {
      "kind": "dump",
      "ticker": "ADBE",
      "t": "2026-07-06T07:04:11-04:00",
      "fire_min": 424,
      "entry": 219.5,
      "rel_vol": null,
      "move_pct": 0.16,
      "target": 217.119,
      "stop": 220.6905,
      "regime": null,
      "graded": true,
      "contract_trace_id": "2026-07-06:live_fire:ADBE:SHORT:dump:706T0704110400:aed48b19",
      "max_up_pct": 0.23,
      "ran": false,
      "mins_to_peak": 19
    },
    {
      "kind": "dump",
      "ticker": "AEHR",
      "t": "2026-07-06T07:04:11-04:00",
      "fire_min": 424,
      "entry": 72.2,
      "rel_vol": null,
      "move_pct": 0.06,
      "target": 70.7088,
      "stop": 72.9456,
      "regime": null,
      "graded": true,
      "contract_trace_id": "2026-07-06:live_fire:AEHR:SHORT:dump:706T0704110400:012b5ef6",
      "max_up_pct": 0.0,
      "ran": false,
      "mins_to_peak": null
    },
    {
      "kind": "dump",
      "ticker": "AHMA",
      "t": "2026-07-06T07:04:11-04:00",
      "fire_min": 424,
      "entry": 2.32,
      "rel_vol": null,
      "move_pct": 2.13,
      "target": 2.1504,
      "stop": 2.4048,
      "regime": null,
      "graded": true,
      "contract_trace_id": "2026-07-06:live_fire:AHMA:SHORT:dump:706T0704110400:8f88013c",
      "max_up_pct": 0.86,
      "ran": false,
      "mins_to_peak": 4
    },
    {
      "kind": "dump",
      "ticker": "ALAB",
      "t": "2026-07-06T07:04:11-04:00",
      "fire_min": 424,
      "entry": 419.0015,
      "rel_vol": null,
      "move_pct": 0.26,
      "target": 411.3165,
      "stop": 422.844,
      "regime": null,
      "graded": true,
      "contract_trace_id": "2026-07-06:live_fire:ALAB:SHORT:dump:706T0704110400:9e3ecc41",
      "max_up_pct": 0.96,
      "ran": false,
      "mins_to_peak": 2
    },
    {
      "kind": "dump",
      "ticker": "AMKR",
      "t": "2026-07-06T07:04:11-04:00",
      "fire_min": 424,
      "entry": 71.95,
      "rel_vol": null,
      "move_pct": 0.0,
      "target": 71.3416,
      "stop": 72.2542,
      "regime": null,
      "graded": true,
      "contract_trace_id": "2026-07-06:live_fire:AMKR:SHORT:dump:706T0704110400:8e260c30",
      "max_up_pct": 0.33,
      "ran": false,
      "mins_to_peak": 5
    },
    {
      "kind": "dump",
      "ticker": "APLD",
      "t": "2026-07-06T07:04:11-04:00",
      "fire_min": 424,
      "entry": 33.85,
      "rel_vol": null,
      "move_pct": 0.62,
      "target": 33.454,
      "stop": 34.048,
      "regime": null,
      "graded": true,
      "contract_trace_id": "2026-07-06:live_fire:APLD:SHORT:dump:706T0704110400:40742edc",
      "max_up_pct": 0.15,
      "ran": false,
      "mins_to_peak": 3
    },
    {
      "kind": "dump",
      "ticker": "AUR",
      "t": "2026-07-06T07:04:11-04:00",
      "fire_min": 424,
      "entry": 6.716,
      "rel_vol": null,
      "move_pct": 0.15,
      "target": 6.5608,
      "stop": 6.7936,
      "regime": null,
      "graded": true,
      "contract_trace_id": "2026-07-06:live_fire:AUR:SHORT:dump:706T0704110400:54c8f238",
      "max_up_pct": 0.09,
      "ran": false,
      "mins_to_peak": 1
    },
    {
      "kind": "dump",
      "ticker": "AXTI",
      "t": "2026-07-06T07:04:11-04:00",
      "fire_min": 424,
      "entry": 59.5522,
      "rel_vol": null,
      "move_pct": 0.67,
      "target": 57.6752,
      "stop": 60.4907,
      "regime": null,
      "graded": true,
      "contract_trace_id": "2026-07-06:live_fire:AXTI:SHORT:dump:706T0704110400:b8357d92",
      "max_up_pct": 0.34,
      "ran": false,
      "mins_to_peak": 0
    },
    {
      "kind": "dump",
      "ticker": "BEAM",
      "t": "2026-07-06T07:04:11-04:00",
      "fire_min": 424,
      "entry": 34.86,
      "rel_vol": null,
      "move_pct": 0.0,
      "target": 33.939,
      "stop": 35.3205,
      "regime": null,
      "graded": true,
      "contract_trace_id": "2026-07-06:live_fire:BEAM:SHORT:dump:706T0704110400:82f608b1",
      "max_up_pct": 0.0,
      "ran": false,
      "mins_to_peak": null
    },
    {
      "kind": "dump",
      "ticker": "BTQ",
      "t": "2026-07-06T07:04:11-04:00",
      "fire_min": 424,
      "entry": 4.96,
      "rel_vol": null,
      "move_pct": 0.0,
      "target": 4.88,
      "stop": 5.0,
      "regime": null,
      "graded": true,
      "contract_trace_id": "2026-07-06:live_fire:BTQ:SHORT:dump:706T0704110400:da85629c",
      "max_up_pct": 0.0,
      "ran": false,
      "mins_to_peak": null
    },
    {
      "kind": "dump",
      "ticker": "CCXI",
      "t": "2026-07-06T07:04:11-04:00",
      "fire_min": 424,
      "entry": 19.1518,
      "rel_vol": null,
      "move_pct": 0.56,
      "target": 17.5758,
      "stop": 19.9398,
      "regime": null,
      "graded": true,
      "contract_trace_id": "2026-07-06:live_fire:CCXI:SHORT:dump:706T0704110400:ba1daa3e",
      "max_up_pct": 1.34,
      "ran": false,
      "mins_to_peak": 7
    },
    {
      "kind": "dump",
      "ticker": "CDE",
      "t": "2026-07-06T07:04:11-04:00",
      "fire_min": 424,
      "entry": 17.6,
      "rel_vol": null,
      "move_pct": 0.4,
      "target": 17.4494,
      "stop": 17.6753,
      "regime": null,
      "graded": true,
      "contract_trace_id": "2026-07-06:live_fire:CDE:SHORT:dump:706T0704110400:eb80dcbc",
      "max_up_pct": 0.11,
      "ran": false,
      "mins_to_peak": 25
    },
    {
      "kind": "dump",
      "ticker": "CEG",
      "t": "2026-07-06T07:04:11-04:00",
      "fire_min": 424,
      "entry": 241.27,
      "rel_vol": null,
      "move_pct": 0.27,
      "target": 239.2228,
      "stop": 242.2936,
      "regime": null,
      "graded": true,
      "contract_trace_id": "2026-07-06:live_fire:CEG:SHORT:dump:706T0704110400:f4d9599a",
      "max_up_pct": 0.0,
      "ran": false,
      "mins_to_peak": null
    },
    {
      "kind": "dump",
      "ticker": "CHWY",
      "t": "2026-07-06T07:04:11-04:00",
      "fire_min": 424,
      "entry": 20.7414,
      "rel_vol": null,
      "move_pct": 0.14,
      "target": 20.3406,
      "stop": 20.9418,
      "regime": null,
      "graded": true,
      "contract_trace_id": "2026-07-06:live_fire:CHWY:SHORT:dump:706T0704110400:f0b014fe",
      "max_up_pct": 0.0,
      "ran": false,
      "mins_to_peak": null
    },
    {
      "kind": "dump",
      "ticker": "CIFR",
      "t": "2026-07-06T07:04:11-04:00",
      "fire_min": 424,
      "entry": 20.6756,
      "rel_vol": null,
      "move_pct": 0.7,
      "target": 20.4438,
      "stop": 20.7915,
      "regime": null,
      "graded": true,
      "contract_trace_id": "2026-07-06:live_fire:CIFR:SHORT:dump:706T0704110400:c894afbb",
      "max_up_pct": 0.41,
      "ran": false,
      "mins_to_peak": 4
    },
    {
      "kind": "dump",
      "ticker": "CLSK",
      "t": "2026-07-06T07:04:11-04:00",
      "fire_min": 424,
      "entry": 12.98,
      "rel_vol": null,
      "move_pct": 0.15,
      "target": 12.7276,
      "stop": 13.1062,
      "regime": null,
      "graded": true,
      "contract_trace_id": "2026-07-06:live_fire:CLSK:SHORT:dump:706T0704110400:6b557163",
      "max_up_pct": 0.62,
      "ran": false,
      "mins_to_peak": 7
    },
    {
      "kind": "dump",
      "ticker": "CRDO",
      "t": "2026-07-06T07:04:11-04:00",
      "fire_min": 424,
      "entry": 249.6686,
      "rel_vol": null,
      "move_pct": 0.0,
      "target": 246.6898,
      "stop": 251.158,
      "regime": null,
      "graded": true,
      "contract_trace_id": "2026-07-06:live_fire:CRDO:SHORT:dump:706T0704110400:715de76a",
      "max_up_pct": 0.41,
      "ran": false,
      "mins_to_peak": 0
    },
    {
      "kind": "dump",
      "ticker": "CRM",
      "t": "2026-07-06T07:04:11-04:00",
      "fire_min": 424,
      "entry": 166.1,
      "rel_vol": null,
      "move_pct": 0.02,
      "target": 164.7742,
      "stop": 166.7629,
      "regime": null,
      "graded": true,
      "contract_trace_id": "2026-07-06:live_fire:CRM:SHORT:dump:706T0704110400:3bc23e17",
      "max_up_pct": 0.24,
      "ran": false,
      "mins_to_peak": 21
    },
    {
      "kind": "dump",
      "ticker": "CRML",
      "t": "2026-07-06T07:04:11-04:00",
      "fire_min": 424,
      "entry": 9.7,
      "rel_vol": null,
      "move_pct": 0.29,
      "target": 9.601,
      "stop": 9.7495,
      "regime": null,
      "graded": true,
      "contract_trace_id": "2026-07-06:live_fire:CRML:SHORT:dump:706T0704110400:5f506d86",
      "max_up_pct": 0.0,
      "ran": false,
      "mins_to_peak": null
    },
    {
      "kind": "dump",
      "ticker": "CRWV",
      "t": "2026-07-06T07:04:11-04:00",
      "fire_min": 424,
      "entry": 83.6,
      "rel_vol": null,
      "move_pct": 0.0,
      "target": 82.45,
      "stop": 84.175,
      "regime": null,
      "graded": true,
      "contract_trace_id": "2026-07-06:live_fire:CRWV:SHORT:dump:706T0704110400:84ef27ff",
      "max_up_pct": 0.22,
      "ran": false,
      "mins_to_peak": 0
    },
    {
      "kind": "dump",
      "ticker": "ELTX",
      "t": "2026-07-06T07:04:11-04:00",
      "fire_min": 424,
      "entry": 3.28,
      "rel_vol": null,
      "move_pct": 1.15,
      "target": 3.1466,
      "stop": 3.3467,
      "regime": null,
      "graded": true,
      "contract_trace_id": "2026-07-06:live_fire:ELTX:SHORT:dump:706T0704110400:7c1e1b20",
      "max_up_pct": 1.22,
      "ran": false,
      "mins_to_peak": 5
    },
    {
      "kind": "dump",
      "ticker": "FCEL",
      "t": "2026-07-06T07:04:11-04:00",
      "fire_min": 424,
      "entry": 28.52,
      "rel_vol": null,
      "move_pct": 0.56,
      "target": 27.6644,
      "stop": 28.9478,
      "regime": null,
      "graded": true,
      "contract_trace_id": "2026-07-06:live_fire:FCEL:SHORT:dump:706T0704110400:c12e3de5",
      "max_up_pct": 0.28,
      "ran": false,
      "mins_to_peak": 8
    },
    {
      "kind": "dump",
      "ticker": "FLY",
      "t": "2026-07-06T07:04:11-04:00",
      "fire_min": 424,
      "entry": 29.352,
      "rel_vol": null,
      "move_pct": 0.14,
      "target": 28.7576,
      "stop": 29.6492,
      "regime": null,
      "graded": true,
      "contract_trace_id": "2026-07-06:live_fire:FLY:SHORT:dump:706T0704110400:9408833a",
      "max_up_pct": 0.55,
      "ran": false,
      "mins_to_peak": 11
    },
    {
      "kind": "dump",
      "ticker": "FRMI",
      "t": "2026-07-06T07:04:11-04:00",
      "fire_min": 424,
      "entry": 8.12,
      "rel_vol": null,
      "move_pct": 0.74,
      "target": 8.0474,
      "stop": 8.1563,
      "regime": null,
      "graded": true,
      "contract_trace_id": "2026-07-06:live_fire:FRMI:SHORT:dump:706T0704110400:e9f840ca",
      "max_up_pct": 0.74,
      "ran": false,
      "mins_to_peak": 22
    },
    {
      "kind": "dump",
      "ticker": "GFI",
      "t": "2026-07-06T07:04:11-04:00",
      "fire_min": 424,
      "entry": 35.36,
      "rel_vol": null,
      "move_pct": 0.37,
      "target": 34.1164,
      "stop": 35.9818,
      "regime": null,
      "graded": true,
      "contract_trace_id": "2026-07-06:live_fire:GFI:SHORT:dump:706T0704110400:65726243",
      "max_up_pct": 0.06,
      "ran": false,
      "mins_to_peak": 0
    },
    {
      "kind": "dump",
      "ticker": "HL",
      "t": "2026-07-06T07:04:11-04:00",
      "fire_min": 424,
      "entry": 16.64,
      "rel_vol": null,
      "move_pct": 0.54,
      "target": 16.4732,
      "stop": 16.7234,
      "regime": null,
      "graded": true,
      "contract_trace_id": "2026-07-06:live_fire:HL:SHORT:dump:706T0704110400:b928e6f1",
      "max_up_pct": 0.18,
      "ran": false,
      "mins_to_peak": 3
    },
    {
      "kind": "dump",
      "ticker": "HMY",
      "t": "2026-07-06T07:04:11-04:00",
      "fire_min": 424,
      "entry": 16.48,
      "rel_vol": null,
      "move_pct": 0.0,
      "target": 15.9332,
      "stop": 16.7534,
      "regime": null,
      "graded": true,
      "contract_trace_id": "2026-07-06:live_fire:HMY:SHORT:dump:706T0704110400:6c8e76f5",
      "max_up_pct": 0.0,
      "ran": false,
      "mins_to_peak": null
    },
    {
      "kind": "dump",
      "ticker": "HOOD",
      "t": "2026-07-06T07:04:11-04:00",
      "fire_min": 424,
      "entry": 113.9002,
      "rel_vol": null,
      "move_pct": 0.03,
      "target": 112.6834,
      "stop": 114.5086,
      "regime": null,
      "graded": true,
      "contract_trace_id": "2026-07-06:live_fire:HOOD:SHORT:dump:706T0704110400:3e40a94a",
      "max_up_pct": 0.0,
      "ran": false,
      "mins_to_peak": null
    },
    {
      "kind": "dump",
      "ticker": "HPE",
      "t": "2026-07-06T07:04:11-04:00",
      "fire_min": 424,
      "entry": 41.9,
      "rel_vol": null,
      "move_pct": 0.05,
      "target": 41.5628,
      "stop": 42.0686,
      "regime": null,
      "graded": true,
      "contract_trace_id": "2026-07-06:live_fire:HPE:SHORT:dump:706T0704110400:c6358bcd",
      "max_up_pct": 0.64,
      "ran": false,
      "mins_to_peak": 15
    },
    {
      "kind": "dump",
      "ticker": "IBRX",
      "t": "2026-07-06T07:04:11-04:00",
      "fire_min": 424,
      "entry": 9.42,
      "rel_vol": null,
      "move_pct": 0.16,
      "target": 9.2822,
      "stop": 9.4889,
      "regime": null,
      "graded": true,
      "contract_trace_id": "2026-07-06:live_fire:IBRX:SHORT:dump:706T0704110400:eb82ec44",
      "max_up_pct": 0.0,
      "ran": false,
      "mins_to_peak": null
    },
    {
      "kind": "dump",
      "ticker": "INFQ",
      "t": "2026-07-06T07:04:11-04:00",
      "fire_min": 424,
      "entry": 12.65,
      "rel_vol": null,
      "move_pct": 0.0,
      "target": 12.4792,
      "stop": 12.7354,
      "regime": null,
      "graded": true,
      "contract_trace_id": "2026-07-06:live_fire:INFQ:SHORT:dump:706T0704110400:5d4cc8cb",
      "max_up_pct": 0.32,
      "ran": false,
      "mins_to_peak": 13
    },
    {
      "kind": "dump",
      "ticker": "IONQ",
      "t": "2026-07-06T07:04:11-04:00",
      "fire_min": 424,
      "entry": 49.72,
      "rel_vol": null,
      "move_pct": 0.0,
      "target": 48.96,
      "stop": 50.1,
      "regime": null,
      "graded": true,
      "contract_trace_id": "2026-07-06:live_fire:IONQ:SHORT:dump:706T0704110400:33295b2d",
      "max_up_pct": 0.18,
      "ran": false,
      "mins_to_peak": 6
    },
    {
      "kind": "dump",
      "ticker": "IREN",
      "t": "2026-07-06T07:04:11-04:00",
      "fire_min": 424,
      "entry": 40.8,
      "rel_vol": null,
      "move_pct": 0.24,
      "target": 39.775,
      "stop": 41.3125,
      "regime": null,
      "graded": true,
      "contract_trace_id": "2026-07-06:live_fire:IREN:SHORT:dump:706T0704110400:ebc78a9d",
      "max_up_pct": 0.0,
      "ran": false,
      "mins_to_peak": null
    },
    {
      "kind": "dump",
      "ticker": "KGC",
      "t": "2026-07-06T07:04:11-04:00",
      "fire_min": 424,
      "entry": 25.05,
      "rel_vol": null,
      "move_pct": 0.05,
      "target": 24.6582,
      "stop": 25.2459,
      "regime": null,
      "graded": true,
      "contract_trace_id": "2026-07-06:live_fire:KGC:SHORT:dump:706T0704110400:c80a2f91",
      "max_up_pct": 0.0,
      "ran": false,
      "mins_to_peak": null
    },
    {
      "kind": "dump",
      "ticker": "MARA",
      "t": "2026-07-06T07:04:11-04:00",
      "fire_min": 424,
      "entry": 12.622,
      "rel_vol": null,
      "move_pct": 0.24,
      "target": 12.4608,
      "stop": 12.7026,
      "regime": null,
      "graded": true,
      "contract_trace_id": "2026-07-06:live_fire:MARA:SHORT:dump:706T0704110400:67052a64",
      "max_up_pct": 0.17,
      "ran": false,
      "mins_to_peak": 8
    },
    {
      "kind": "dump",
      "ticker": "MRNA",
      "t": "2026-07-06T07:04:11-04:00",
      "fire_min": 424,
      "entry": 79.26,
      "rel_vol": null,
      "move_pct": 0.04,
      "target": 77.7206,
      "stop": 80.0297,
      "regime": null,
      "graded": true,
      "contract_trace_id": "2026-07-06:live_fire:MRNA:SHORT:dump:706T0704110400:d6c656a5",
      "max_up_pct": 0.33,
      "ran": false,
      "mins_to_peak": 23
    }
  ]
}